{"config":{"output_file":null,"full_docs":false,"pub_only":false,"reachable_only":false,"distro_crate":false,"signatures":false,"borrow_data":false},"version":"0.19.1","compilation":{"directory":"/home/amir/Documents/Learn_Rust3/polymorphism","program":"/home/amir/.rustup/toolchains/stable-x86_64-unknown-linux-gnu/bin/rls","arguments":[],"output":"/home/amir/Documents/Learn_Rust3/polymorphism/target/rls/debug/deps/libpolymorphism-e4d94937777bc78c.rmeta"},"prelude":{"crate_id":{"name":"polymorphism","disambiguator":[10638858672672905645,0]},"crate_root":"src","external_crates":[{"file_name":"/home/amir/Documents/Learn_Rust3/polymorphism/src/main.rs","num":1,"id":{"name":"std","disambiguator":[266559774140218402,0]}},{"file_name":"/home/amir/Documents/Learn_Rust3/polymorphism/src/main.rs","num":2,"id":{"name":"core","disambiguator":[11763967750977672065,0]}},{"file_name":"/home/amir/Documents/Learn_Rust3/polymorphism/src/main.rs","num":3,"id":{"name":"compiler_builtins","disambiguator":[10106063140927293834,0]}},{"file_name":"/home/amir/Documents/Learn_Rust3/polymorphism/src/main.rs","num":4,"id":{"name":"rustc_std_workspace_core","disambiguator":[7335734036341381276,0]}},{"file_name":"/home/amir/Documents/Learn_Rust3/polymorphism/src/main.rs","num":5,"id":{"name":"alloc","disambiguator":[6464017807659102018,0]}},{"file_name":"/home/amir/Documents/Learn_Rust3/polymorphism/src/main.rs","num":6,"id":{"name":"libc","disambiguator":[308958561119313021,0]}},{"file_name":"/home/amir/Documents/Learn_Rust3/polymorphism/src/main.rs","num":7,"id":{"name":"unwind","disambiguator":[16887813381474488870,0]}},{"file_name":"/home/amir/Documents/Learn_Rust3/polymorphism/src/main.rs","num":8,"id":{"name":"cfg_if","disambiguator":[18138047136180876386,0]}},{"file_name":"/home/amir/Documents/Learn_Rust3/polymorphism/src/main.rs","num":9,"id":{"name":"miniz_oxide","disambiguator":[16720472299414307338,0]}},{"file_name":"/home/amir/Documents/Learn_Rust3/polymorphism/src/main.rs","num":10,"id":{"name":"rustc_std_workspace_alloc","disambiguator":[5531791840279234689,0]}},{"file_name":"/home/amir/Documents/Learn_Rust3/polymorphism/src/main.rs","num":11,"id":{"name":"adler","disambiguator":[2995214285932701362,0]}},{"file_name":"/home/amir/Documents/Learn_Rust3/polymorphism/src/main.rs","num":12,"id":{"name":"hashbrown","disambiguator":[17222063258158154566,0]}},{"file_name":"/home/amir/Documents/Learn_Rust3/polymorphism/src/main.rs","num":13,"id":{"name":"std_detect","disambiguator":[7245893233601562531,0]}},{"file_name":"/home/amir/Documents/Learn_Rust3/polymorphism/src/main.rs","num":14,"id":{"name":"rustc_demangle","disambiguator":[4839492760463372304,0]}},{"file_name":"/home/amir/Documents/Learn_Rust3/polymorphism/src/main.rs","num":15,"id":{"name":"addr2line","disambiguator":[1226649225884195013,0]}},{"file_name":"/home/amir/Documents/Learn_Rust3/polymorphism/src/main.rs","num":16,"id":{"name":"gimli","disambiguator":[12460504831400488231,0]}},{"file_name":"/home/amir/Documents/Learn_Rust3/polymorphism/src/main.rs","num":17,"id":{"name":"object","disambiguator":[2536915343129323536,0]}},{"file_name":"/home/amir/Documents/Learn_Rust3/polymorphism/src/main.rs","num":18,"id":{"name":"memchr","disambiguator":[4342342869490546433,0]}},{"file_name":"/home/amir/Documents/Learn_Rust3/polymorphism/src/main.rs","num":19,"id":{"name":"panic_unwind","disambiguator":[2139538778087984071,0]}}],"span":{"file_name":"src/main.rs","byte_start":1626,"byte_end":2020,"line_start":75,"line_end":96,"column_start":1,"column_end":2}},"imports":[{"kind":"Use","ref_id":{"krate":2,"index":2679},"span":{"file_name":"src/main.rs","byte_start":1642,"byte_end":1647,"line_start":75,"line_end":75,"column_start":17,"column_end":22},"alias_span":null,"name":"Clone","value":"","parent":{"krate":0,"index":0}},{"kind":"Use","ref_id":{"krate":2,"index":2682},"span":{"file_name":"src/main.rs","byte_start":1642,"byte_end":1647,"line_start":75,"line_end":75,"column_start":17,"column_end":22},"alias_span":null,"name":"Clone","value":"","parent":{"krate":0,"index":0}}],"defs":[{"kind":"Mod","id":{"krate":0,"index":0},"span":{"file_name":"src/main.rs","byte_start":1626,"byte_end":2020,"line_start":75,"line_end":96,"column_start":1,"column_end":2},"name":"","qualname":"::","value":"src/main.rs","parent":null,"children":[{"krate":0,"index":1},{"krate":0,"index":2},{"krate":0,"index":3},{"krate":0,"index":4},{"krate":0,"index":9},{"krate":0,"index":12},{"krate":0,"index":6},{"krate":0,"index":8}],"decl_id":null,"docs":"","sig":null,"attributes":[]},{"kind":"Struct","id":{"krate":0,"index":9},"span":{"file_name":"src/main.rs","byte_start":1674,"byte_end":1687,"line_start":78,"line_end":78,"column_start":8,"column_end":21},"name":"YouCanCloneMe","qualname":"::YouCanCloneMe","value":"YouCanCloneMe { name, age }","parent":null,"children":[{"krate":0,"index":10},{"krate":0,"index":11}],"decl_id":null,"docs":"","sig":null,"attributes":[]},{"kind":"Field","id":{"krate":0,"index":10},"span":{"file_name":"src/main.rs","byte_start":1694,"byte_end":1698,"line_start":79,"line_end":79,"column_start":5,"column_end":9},"name":"name","qualname":"::YouCanCloneMe::name","value":"std::string::String","parent":{"krate":0,"index":9},"children":[],"decl_id":null,"docs":"","sig":null,"attributes":[]},{"kind":"Field","id":{"krate":0,"index":11},"span":{"file_name":"src/main.rs","byte_start":1712,"byte_end":1715,"line_start":80,"line_end":80,"column_start":5,"column_end":8},"name":"age","qualname":"::YouCanCloneMe::age","value":"u8","parent":{"krate":0,"index":9},"children":[],"decl_id":null,"docs":"","sig":null,"attributes":[]},{"kind":"Local","id":{"krate":0,"index":1073741831},"span":{"file_name":"src/main.rs","byte_start":1769,"byte_end":1773,"line_start":85,"line_end":85,"column_start":15,"column_end":19},"name":"self","qualname":"<YouCanCloneMe as std::clone::Clone>::clone::self","value":"&YouCanCloneMe","parent":null,"children":[],"decl_id":null,"docs":"","sig":null,"attributes":[]},{"kind":"Method","id":{"krate":0,"index":7},"span":{"file_name":"src/main.rs","byte_start":1762,"byte_end":1767,"line_start":85,"line_end":85,"column_start":8,"column_end":13},"name":"clone","qualname":"<YouCanCloneMe as std::clone::Clone>::clone","value":"fn clone(&Self) -> Self","parent":{"krate":2,"index":2679},"children":[],"decl_id":{"krate":2,"index":2680},"docs":"","sig":null,"attributes":[]},{"kind":"Function","id":{"krate":0,"index":8},"span":{"file_name":"src/main.rs","byte_start":1867,"byte_end":1871,"line_start":90,"line_end":90,"column_start":4,"column_end":8},"name":"main","qualname":"::main","value":"fn main()","parent":null,"children":[],"decl_id":null,"docs":"","sig":null,"attributes":[]},{"kind":"Local","id":{"krate":0,"index":1879048200},"span":{"file_name":"src/main.rs","byte_start":1884,"byte_end":1889,"line_start":91,"line_end":91,"column_start":9,"column_end":14},"name":"yaroo","qualname":"yaroo$HirId { owner: DefId(0:8 ~ polymorphism[93a4]::main), local_id: 14 }","value":"YouCanCloneMe","parent":null,"children":[],"decl_id":null,"docs":"","sig":null,"attributes":[]}],"impls":[{"id":0,"kind":"Direct","span":{"file_name":"src/main.rs","byte_start":1739,"byte_end":1752,"line_start":84,"line_end":84,"column_start":16,"column_end":29},"value":"","parent":null,"children":[{"krate":0,"index":7}],"docs":"","sig":null,"attributes":[]}],"refs":[{"kind":"Mod","span":{"file_name":"src/main.rs","byte_start":1630,"byte_end":1633,"line_start":75,"line_end":75,"column_start":5,"column_end":8},"ref_id":{"krate":1,"index":0}},{"kind":"Mod","span":{"file_name":"src/main.rs","byte_start":1635,"byte_end":1640,"line_start":75,"line_end":75,"column_start":10,"column_end":15},"ref_id":{"krate":2,"index":2675}},{"kind":"Type","span":{"file_name":"src/main.rs","byte_start":1700,"byte_end":1706,"line_start":79,"line_end":79,"column_start":11,"column_end":17},"ref_id":{"krate":5,"index":7626}},{"kind":"Variable","span":{"file_name":"src/main.rs","byte_start":1694,"byte_end":1698,"line_start":79,"line_end":79,"column_start":5,"column_end":9},"ref_id":{"krate":0,"index":10}},{"kind":"Variable","span":{"file_name":"src/main.rs","byte_start":1712,"byte_end":1715,"line_start":80,"line_end":80,"column_start":5,"column_end":8},"ref_id":{"krate":0,"index":11}},{"kind":"Type","span":{"file_name":"src/main.rs","byte_start":1739,"byte_end":1752,"line_start":84,"line_end":84,"column_start":16,"column_end":29},"ref_id":{"krate":0,"index":9}},{"kind":"Type","span":{"file_name":"src/main.rs","byte_start":1729,"byte_end":1734,"line_start":84,"line_end":84,"column_start":6,"column_end":11},"ref_id":{"krate":2,"index":2679}},{"kind":"Type","span":{"file_name":"src/main.rs","byte_start":1800,"byte_end":1813,"line_start":86,"line_end":86,"column_start":16,"column_end":29},"ref_id":{"krate":0,"index":9}},{"kind":"Variable","span":{"file_name":"src/main.rs","byte_start":1814,"byte_end":1818,"line_start":86,"line_end":86,"column_start":30,"column_end":34},"ref_id":{"krate":0,"index":10}},{"kind":"Function","span":{"file_name":"src/main.rs","byte_start":1830,"byte_end":1835,"line_start":86,"line_end":86,"column_start":46,"column_end":51},"ref_id":{"krate":2,"index":2680}},{"kind":"Variable","span":{"file_name":"src/main.rs","byte_start":1820,"byte_end":1824,"line_start":86,"line_end":86,"column_start":36,"column_end":40},"ref_id":{"krate":0,"index":1073741831}},{"kind":"Variable","span":{"file_name":"src/main.rs","byte_start":1825,"byte_end":1829,"line_start":86,"line_end":86,"column_start":41,"column_end":45},"ref_id":{"krate":0,"index":10}},{"kind":"Variable","span":{"file_name":"src/main.rs","byte_start":1839,"byte_end":1842,"line_start":86,"line_end":86,"column_start":55,"column_end":58},"ref_id":{"krate":0,"index":11}},{"kind":"Variable","span":{"file_name":"src/main.rs","byte_start":1844,"byte_end":1848,"line_start":86,"line_end":86,"column_start":60,"column_end":64},"ref_id":{"krate":0,"index":1073741831}},{"kind":"Variable","span":{"file_name":"src/main.rs","byte_start":1849,"byte_end":1852,"line_start":86,"line_end":86,"column_start":65,"column_end":68},"ref_id":{"krate":0,"index":11}},{"kind":"Type","span":{"file_name":"src/main.rs","byte_start":1892,"byte_end":1905,"line_start":91,"line_end":91,"column_start":17,"column_end":30},"ref_id":{"krate":0,"index":9}},{"kind":"Variable","span":{"file_name":"src/main.rs","byte_start":1916,"byte_end":1920,"line_start":92,"line_end":92,"column_start":9,"column_end":13},"ref_id":{"krate":0,"index":10}},{"kind":"Function","span":{"file_name":"src/main.rs","byte_start":1930,"byte_end":1934,"line_start":92,"line_end":92,"column_start":23,"column_end":27},"ref_id":{"krate":2,"index":2965}},{"kind":"Type","span":{"file_name":"src/main.rs","byte_start":1922,"byte_end":1928,"line_start":92,"line_end":92,"column_start":15,"column_end":21},"ref_id":{"krate":5,"index":7626}},{"kind":"Variable","span":{"file_name":"src/main.rs","byte_start":1952,"byte_end":1955,"line_start":93,"line_end":93,"column_start":9,"column_end":12},"ref_id":{"krate":0,"index":11}},{"kind":"Function","span":{"file_name":"src/main.rs","byte_start":2009,"byte_end":2014,"line_start":95,"line_end":95,"column_start":43,"column_end":48},"ref_id":{"krate":2,"index":2680}},{"kind":"Variable","span":{"file_name":"src/main.rs","byte_start":2003,"byte_end":2008,"line_start":95,"line_end":95,"column_start":37,"column_end":42},"ref_id":{"krate":0,"index":1879048200}},{"kind":"Mod","span":{"file_name":"/rustc/fe5b13d681f25ee6474be29d748c65adcd91f69e/library/std/src/macros.rs","byte_start":27757,"byte_end":27790,"line_start":103,"line_end":103,"column_start":28,"column_end":61},"ref_id":{"krate":2,"index":9311}},{"kind":"Mod","span":{"file_name":"/rustc/fe5b13d681f25ee6474be29d748c65adcd91f69e/library/std/src/macros.rs","byte_start":27757,"byte_end":27790,"line_start":103,"line_end":103,"column_start":28,"column_end":61},"ref_id":{"krate":2,"index":9625}},{"kind":"Mod","span":{"file_name":"/rustc/fe5b13d681f25ee6474be29d748c65adcd91f69e/library/std/src/macros.rs","byte_start":27757,"byte_end":27790,"line_start":103,"line_end":103,"column_start":28,"column_end":61},"ref_id":{"krate":2,"index":9626}},{"kind":"Mod","span":{"file_name":"/rustc/fe5b13d681f25ee6474be29d748c65adcd91f69e/library/std/src/macros.rs","byte_start":27757,"byte_end":27790,"line_start":103,"line_end":103,"column_start":28,"column_end":61},"ref_id":{"krate":2,"index":9311}},{"kind":"Mod","span":{"file_name":"/rustc/fe5b13d681f25ee6474be29d748c65adcd91f69e/library/std/src/macros.rs","byte_start":27757,"byte_end":27790,"line_start":103,"line_end":103,"column_start":28,"column_end":61},"ref_id":{"krate":2,"index":9625}},{"kind":"Mod","span":{"file_name":"/rustc/fe5b13d681f25ee6474be29d748c65adcd91f69e/library/std/src/macros.rs","byte_start":27757,"byte_end":27790,"line_start":103,"line_end":103,"column_start":28,"column_end":61},"ref_id":{"krate":2,"index":9626}}],"macro_refs":[],"relations":[{"span":{"file_name":"src/main.rs","byte_start":1739,"byte_end":1752,"line_start":84,"line_end":84,"column_start":16,"column_end":29},"kind":{"Impl":{"id":0}},"from":{"krate":0,"index":9},"to":{"krate":2,"index":2679}}]}